Workbook

Sheet Database
A1: Document_Symbol | B1: Date | C1: Title | D1: WTO_Forum | E1: Participant | F1: Governance function | G1: Domain Family | H1: Reference_Paragraph | I1: Sub-Domain 1 | J1: Sub-Domain 2 | K1: Sub-Domain 3 | L1: Measure | M1: Measure_Owner | N1: Governance Dimension 1 | O1: Governance Topic 1 | P1: Governance Dimension 2 | Q1: Governance Topic 2 | R1: Governance Dimension 3 | S1: Governance Topic 3 | T1: Governance Dimension 4 | U1: Governance Topic 4 | V1: Governance Dimension 5 | W1: Governance Topic 5 | X1: Confidence | Y1: Interaction_Summary
A2: G/C/M/153 | B2: 46177 | C2: Minutes of the Meeting of the Council for Trade in Goods (27-28 Nov 2025) | D2: CTG | E2: India | F2: Information Sharing | G2: Industrial Policy & Economic Security | H2: 9.21 | I2: Export/Import Controls | J2: Carbon Measures | K2: National/Economic Security | L2: No Specific Measure | M2: Not applicable | N2: =_xlfn.XLOOKUP(O2,'Governance Dimension_Topics'!$C$3:$C$16,'Governance Dimension_Topics'!$B$3:$B$16,"None",0) -> Political Economy | O2: Economic Security & Strategic Autonomy | P2: =_xlfn.XLOOKUP(Q2,'Governance Dimension_Topics'!$C$3:$C$16,'Governance Dimension_Topics'!$B$3:$B$16,"None",0) -> Development | Q2: Policy Space | R2: =_xlfn.XLOOKUP(S2,'Governance Dimension_Topics'!$C$3:$C$16,'Governance Dimension_Topics'!$B$3:$B$16,"None",0) -> Political Economy | S2: Economic Security & Strategic Autonomy | X2: High | Y2: Raised concerns that tariffs, NTMs, unilateral green measures and export controls are fragmenting trade and stressing global supply chains.
A3: G/C/M/153 | B3: 46177 | C3: Minutes of the Meeting of the Council for Trade in Goods (27-28 Nov 2025) | D3: CTG | E3: China | F3: Information Sharing | G3: Industrial Policy & Economic Security | H3: 9.23-9.24 | L3: No Specific Measure | M3: Not applicable | N3: =_xlfn.XLOOKUP(O3,'Governance Dimension_Topics'!$C$3:$C$16,'Governance Dimension_Topics'!$B$3:$B$16,"None",0) -> Economic | O3: Market Access & Trade Effects | P3: =_xlfn.XLOOKUP(Q3,'Governance Dimension_Topics'!$C$3:$C$16,'Governance Dimension_Topics'!$B$3:$B$16,"None",0) -> Institutional | Q3: International Cooperation | R3: =_xlfn.XLOOKUP(S3,'Governance Dimension_Topics'!$C$3:$C$16,'Governance Dimension_Topics'!$B$3:$B$16,"None",0) -> Legal | S3: WTO Consistency & Legal Interpretation | X3: High | Y3: Expressed concern over reciprocal tariffs and supported dialogue and WTO reform.
A4: G/C/M/153 | B4: 46177 | C4: Minutes of the Meeting of the Council for Trade in Goods (27-28 Nov 2025) | D4: CTG | E4: Republic of Korea | F4: Information Sharing | G4: Industrial Policy & Economic Security | H4: 9.26 | I4: National/Economic Security | L4: No Specific Measure | M4: Not applicable | N4: =_xlfn.XLOOKUP(O4,'Governance Dimension_Topics'!$C$3:$C$16,'Governance Dimension_Topics'!$B$3:$B$16,"None",0) -> Political Economy | O4: Economic Security & Strategic Autonomy | P4: =_xlfn.XLOOKUP(Q4,'Governance Dimension_Topics'!$C$3:$C$16,'Governance Dimension_Topics'!$B$3:$B$16,"None",0) -> Economic | Q4: Competitiveness | R4: =_xlfn.XLOOKUP(S4,'Governance Dimension_Topics'!$C$3:$C$16,'Governance Dimension_Topics'!$B$3:$B$16,"None",0) -> Legal | S4: Transparency & Due Process | X4: High | Y4: Highlighted negative impacts of trade policy shifts on investment decisions, supply chains and key sectors.
A5: G/C/M/153 | B5: 46177 | C5: Minutes of the Meeting of the Council for Trade in Goods (27-28 Nov 2025) | D5: CTG | E5: Russian Federation | F5: Information Sharing | G5: Industrial Policy & Economic Security | H5: 9.28-9.32 | I5: Export/Import Controls | J5: Carbon Measures | K5: National/Economic Security | L5: No Specific Measure | M5: Not applicable | N5: =_xlfn.XLOOKUP(O5,'Governance Dimension_Topics'!$C$3:$C$16,'Governance Dimension_Topics'!$B$3:$B$16,"None",0) -> Legal | O5: WTO Consistency & Legal Interpretation | P5: =_xlfn.XLOOKUP(Q5,'Governance Dimension_Topics'!$C$3:$C$16,'Governance Dimension_Topics'!$B$3:$B$16,"None",0) -> Legal | Q5: WTO Consistency & Legal Interpretation | R5: =_xlfn.XLOOKUP(S5,'Governance Dimension_Topics'!$C$3:$C$16,'Governance Dimension_Topics'!$B$3:$B$16,"None",0) -> Political Economy | S5: Economic Security & Strategic Autonomy | T5: =_xlfn.XLOOKUP(U5,'Governance Dimension_Topics'!$C$3:$C$16,'Governance Dimension_Topics'!$B$3:$B$16,"None",0) -> Regulatory | U5: Interoperability & Equivalence | X5: Medium | Y5: Criticized unilateral restrictions and regulations justified by environmental protection and national security.
A6: G/C/M/153 | B6: 46177 | C6: Minutes of the Meeting of the Council for Trade in Goods (27-28 Nov 2025) | D6: CTG | E6: Singapore | F6: Information Sharing | G6: Industrial Policy & Economic Security | H6: 9.41-9.42 | I6: National/Economic Security | L6: No Specific Measure | M6: Not applicable | N6: =_xlfn.XLOOKUP(O6,'Governance Dimension_Topics'!$C$3:$C$16,'Governance Dimension_Topics'!$B$3:$B$16,"None",0) -> Political Economy | O6: Economic Security & Strategic Autonomy | P6: =_xlfn.XLOOKUP(Q6,'Governance Dimension_Topics'!$C$3:$C$16,'Governance Dimension_Topics'!$B$3:$B$16,"None",0) -> Institutional | Q6: International Cooperation | R6: =_xlfn.XLOOKUP(S6,'Governance Dimension_Topics'!$C$3:$C$16,'Governance Dimension_Topics'!$B$3:$B$16,"None",0) -> Institutional | S6: Institutional Capacity & Coordination | X6: High | Y6: Called for dialogue, cooperation and WTO reform to address disruptions to supply chains and markets.
A7: G/C/M/153 | B7: 46177 | C7: Minutes of the Meeting of the Council for Trade in Goods (27-28 Nov 2025) | D7: CTG | E7: United States | F7: Information Sharing | G7: Industrial Policy & Economic Security | H7: 9.49-9.55 | I7: National/Economic Security | L7: No Specific Measure | M7: Not applicable | X7: High | Y7: Defended a production-oriented trade policy emphasizing resilience, critical minerals, semiconductors and differentiated trade relationships.
A8: G/C/M/153 | B8: 46177 | C8: Minutes of the Meeting of the Council for Trade in Goods (27-28 Nov 2025) | D8: CTG | E8: Japan | F8: Concern Raised | G8: Climate & Sustainability | H8: 10.3.1 | I8: Other Climate/Sustainability Measures | L8: Fluorinated GHG Reg. | M8: European Union | N8: =_xlfn.XLOOKUP(O8,'Governance Dimension_Topics'!$C$3:$C$16,'Governance Dimension_Topics'!$B$3:$B$16,"None",0) -> Technical | O8: Technical Basis | P8: =_xlfn.XLOOKUP(Q8,'Governance Dimension_Topics'!$C$3:$C$16,'Governance Dimension_Topics'!$B$3:$B$16,"None",0) -> Legal | Q8: WTO Consistency & Legal Interpretation | X8: High | Y8: Raised concerns regarding EU F-Gas regulation and transition impacts.
A9: G/C/M/153 | B9: 46177 | C9: Minutes of the Meeting of the Council for Trade in Goods (27-28 Nov 2025) | D9: CTG | E9: United States | F9: Concern Raised | G9: Climate & Sustainability | H9: 10.3.1 | I9: Other Climate/Sustainability Measures | L9: Fluorinated GHG Reg. | M9: European Union | N9: =_xlfn.XLOOKUP(O9,'Governance Dimension_Topics'!$C$3:$C$16,'Governance Dimension_Topics'!$B$3:$B$16,"None",0) -> Economic | O9: Market Access & Trade Effects | P9: =_xlfn.XLOOKUP(Q9,'Governance Dimension_Topics'!$C$3:$C$16,'Governance Dimension_Topics'!$B$3:$B$16,"None",0) -> Economic | Q9: Market Access & Trade Effects | X9: High | Y9: Supported concerns regarding EU F-Gas regulation.
A10: G/C/M/153 | B10: 46177 | C10: Minutes of the Meeting of the Council for Trade in Goods (27-28 Nov 2025) | D10: CTG | E10: European Union | F10: Defence/Explanation | G10: Climate & Sustainability | H10: 10.3.1 | I10: Other Climate/Sustainability Measures | J10: Other Climate/Sustainability Measures | L10: Fluorinated GHG Reg. | M10: European Union | X10: High | Y10: Defended the F-Gas regulation and its climate objectives.
A11: G/C/M/153 | B11: 46177 | C11: Minutes of the Meeting of the Council for Trade in Goods (27-28 Nov 2025) | D11: CTG | E11: United States | F11: Concern Raised | G11: Climate & Sustainability | H11: 10.3.2 | I11: Other Climate/Sustainability Measures | L11: MRLs | M11: European Union | N11: =_xlfn.XLOOKUP(O11,'Governance Dimension_Topics'!$C$3:$C$16,'Governance Dimension_Topics'!$B$3:$B$16,"None",0) -> Legal | O11: WTO Consistency & Legal Interpretation | P11: =_xlfn.XLOOKUP(Q11,'Governance Dimension_Topics'!$C$3:$C$16,'Governance Dimension_Topics'!$B$3:$B$16,"None",0) -> Economic | Q11: Market Access & Trade Effects | X11: High | Y11: Raised concerns over EU pesticide residue rules.
A12: G/C/M/153 | B12: 46177 | C12: Minutes of the Meeting of the Council for Trade in Goods (27-28 Nov 2025) | D12: CTG | E12: Brazil | F12: Concern Raised | G12: Climate & Sustainability | H12: 10.3.2 | I12: Other Climate/Sustainability Measures | L12: MRLs | M12: European Union | N12: =_xlfn.XLOOKUP(O12,'Governance Dimension_Topics'!$C$3:$C$16,'Governance Dimension_Topics'!$B$3:$B$16,"None",0) -> Technical | O12: Technical Basis | P12: =_xlfn.XLOOKUP(Q12,'Governance Dimension_Topics'!$C$3:$C$16,'Governance Dimension_Topics'!$B$3:$B$16,"None",0) -> Economic | Q12: Market Access & Trade Effects | R12: =_xlfn.XLOOKUP(S12,'Governance Dimension_Topics'!$C$3:$C$16,'Governance Dimension_Topics'!$B$3:$B$16,"None",0) -> Legal | S12: Transparency & Due Process | T12: =_xlfn.XLOOKUP(U12,'Governance Dimension_Topics'!$C$3:$C$16,'Governance Dimension_Topics'!$B$3:$B$16,"None",0) -> Development | U12: Policy Space | X12: High | Y12: Questioned scientific justification.
A13: G/C/M/153 | B13: 46177 | C13: Minutes of the Meeting of the Council for Trade in Goods (27-28 Nov 2025) | D13: CTG | E13: Australia | F13: Concern Raised | G13: Climate & Sustainability | H13: 10.3.2 | I13: Other Climate/Sustainability Measures | L13: MRLs | M13: European Union | N13: =_xlfn.XLOOKUP(O13,'Governance Dimension_Topics'!$C$3:$C$16,'Governance Dimension_Topics'!$B$3:$B$16,"None",0) -> Economic | O13: Market Access & Trade Effects | P13: =_xlfn.XLOOKUP(Q13,'Governance Dimension_Topics'!$C$3:$C$16,'Governance Dimension_Topics'!$B$3:$B$16,"None",0) -> Development | Q13: Policy Space | X13: Medium | Y13: Raised trade concerns regarding implementation.
A14: G/C/M/153 | B14: 46177 | C14: Minutes of the Meeting of the Council for Trade in Goods (27-28 Nov 2025) | D14: CTG | E14: Indonesia | F14: Concern Raised | G14: Climate & Sustainability | H14: 10.3.2 | I14: Other Climate/Sustainability Measures | L14: MRLs | M14: European Union | N14: =_xlfn.XLOOKUP(O14,'Governance Dimension_Topics'!$C$3:$C$16,'Governance Dimension_Topics'!$B$3:$B$16,"None",0) -> Development | O14: Policy Space | P14: =_xlfn.XLOOKUP(Q14,'Governance Dimension_Topics'!$C$3:$C$16,'Governance Dimension_Topics'!$B$3:$B$16,"None",0) -> Legal | Q14: WTO Consistency & Legal Interpretation | R14: =_xlfn.XLOOKUP(S14,'Governance Dimension_Topics'!$C$3:$C$16,'Governance Dimension_Topics'!$B$3:$B$16,"None",0) -> Economic | S14: Market Access & Trade Effects | X14: Medium | Y14: Expressed concern regarding impacts on exporters.
A15: G/C/M/153 | B15: 46177 | C15: Minutes of the Meeting of the Council for Trade in Goods (27-28 Nov 2025) | D15: CTG | E15: Argentina | F15: Concern Raised | G15: Climate & Sustainability | H15: 10.3.2 | I15: Other Climate/Sustainability Measures | L15: MRLs | M15: European Union | N15: =_xlfn.XLOOKUP(O15,'Governance Dimension_Topics'!$C$3:$C$16,'Governance Dimension_Topics'!$B$3:$B$16,"None",0) -> Technical | O15: Technical Basis | X15: High | Y15: Supported concerns regarding scientific basis.
A16: G/C/M/153 | B16: 46177 | C16: Minutes of the Meeting of the Council for Trade in Goods (27-28 Nov 2025) | D16: CTG | E16: Ecuador | F16: Concern Raised | G16: Climate & Sustainability | H16: 10.3.2 | I16: Other Climate/Sustainability Measures | L16: MRLs | M16: European Union | N16: =_xlfn.XLOOKUP(O16,'Governance Dimension_Topics'!$C$3:$C$16,'Governance Dimension_Topics'!$B$3:$B$16,"None",0) -> Economic | O16: Market Access & Trade Effects | P16: =_xlfn.XLOOKUP(Q16,'Governance Dimension_Topics'!$C$3:$C$16,'Governance Dimension_Topics'!$B$3:$B$16,"None",0) -> Legal | Q16: WTO Consistency & Legal Interpretation | R16: =_xlfn.XLOOKUP(S16,'Governance Dimension_Topics'!$C$3:$C$16,'Governance Dimension_Topics'!$B$3:$B$16,"None",0) -> Development | S16: Policy Space | X16: Medium | Y16: Supported co-sponsors' concerns.
A17: G/C/M/153 | B17: 46177 | C17: Minutes of the Meeting of the Council for Trade in Goods (27-28 Nov 2025) | D17: CTG | E17: Paraguay | F17: Concern Raised | G17: Climate & Sustainability | H17: 10.3.2 | I17: Other Climate/Sustainability Measures | L17: MRLs | M17: European Union | N17: =_xlfn.XLOOKUP(O17,'Governance Dimension_Topics'!$C$3:$C$16,'Governance Dimension_Topics'!$B$3:$B$16,"None",0) -> Economic | O17: Market Access & Trade Effects | P17: =_xlfn.XLOOKUP(Q17,'Governance Dimension_Topics'!$C$3:$C$16,'Governance Dimension_Topics'!$B$3:$B$16,"None",0) -> Legal | Q17: WTO Consistency & Legal Interpretation | R17: =_xlfn.XLOOKUP(S17,'Governance Dimension_Topics'!$C$3:$C$16,'Governance Dimension_Topics'!$B$3:$B$16,"None",0) -> Legal | S17: WTO Consistency & Legal Interpretation | T17: =_xlfn.XLOOKUP(U17,'Governance Dimension_Topics'!$C$3:$C$16,'Governance Dimension_Topics'!$B$3:$B$16,"None",0) -> Technical | U17: Technical Basis | X17: Medium | Y17: Supported co-sponsors' concerns.
A18: G/C/M/153 | B18: 46177 | C18: Minutes of the Meeting of the Council for Trade in Goods (27-28 Nov 2025) | D18: CTG | E18: Guatemala | F18: Concern Raised | G18: Climate & Sustainability | H18: 10.3.2 | I18: Other Climate/Sustainability Measures | L18: MRLs | M18: European Union | N18: =_xlfn.XLOOKUP(O18,'Governance Dimension_Topics'!$C$3:$C$16,'Governance Dimension_Topics'!$B$3:$B$16,"None",0) -> Economic | O18: Market Access & Trade Effects | P18: =_xlfn.XLOOKUP(Q18,'Governance Dimension_Topics'!$C$3:$C$16,'Governance Dimension_Topics'!$B$3:$B$16,"None",0) -> Legal | Q18: WTO Consistency & Legal Interpretation | X18: Medium | Y18: Supported concerns on residue measures.
A19: G/C/M/153 | B19: 46177 | C19: Minutes of the Meeting of the Council for Trade in Goods (27-28 Nov 2025) | D19: CTG | E19: India | F19: Concern Raised | G19: Climate & Sustainability | H19: 10.3.2 | I19: Other Climate/Sustainability Measures | L19: MRLs | M19: European Union | N19: =_xlfn.XLOOKUP(O19,'Governance Dimension_Topics'!$C$3:$C$16,'Governance Dimension_Topics'!$B$3:$B$16,"None",0) -> Technical | O19: Technical Basis | X19: Medium | Y19: Raised concerns on implementation and evidence base.
A20: G/C/M/153 | B20: 46177 | C20: Minutes of the Meeting of the Council for Trade in Goods (27-28 Nov 2025) | D20: CTG | E20: Colombia | F20: Concern Raised | G20: Climate & Sustainability | H20: 10.3.2 | I20: Other Climate/Sustainability Measures | L20: MRLs | M20: European Union | N20: =_xlfn.XLOOKUP(O20,'Governance Dimension_Topics'!$C$3:$C$16,'Governance Dimension_Topics'!$B$3:$B$16,"None",0) -> Economic | O20: Market Access & Trade Effects | P20: =_xlfn.XLOOKUP(Q20,'Governance Dimension_Topics'!$C$3:$C$16,'Governance Dimension_Topics'!$B$3:$B$16,"None",0) -> Technical | Q20: Technical Basis | X20: Medium | Y20: Supported concerns raised by exporters.
A21: G/C/M/153 | B21: 46177 | C21: Minutes of the Meeting of the Council for Trade in Goods (27-28 Nov 2025) | D21: CTG | E21: Uruguay | F21: Concern Raised | G21: Climate & Sustainability | H21: 10.3.2 | I21: Other Climate/Sustainability Measures | L21: MRLs | M21: European Union | N21: =_xlfn.XLOOKUP(O21,'Governance Dimension_Topics'!$C$3:$C$16,'Governance Dimension_Topics'!$B$3:$B$16,"None",0) -> Economic | O21: Market Access & Trade Effects | P21: =_xlfn.XLOOKUP(Q21,'Governance Dimension_Topics'!$C$3:$C$16,'Governance Dimension_Topics'!$B$3:$B$16,"None",0) -> Legal | Q21: WTO Consistency & Legal Interpretation | R21: =_xlfn.XLOOKUP(S21,'Governance Dimension_Topics'!$C$3:$C$16,'Governance Dimension_Topics'!$B$3:$B$16,"None",0) -> Development | S21: Policy Space | X21: Medium | Y21: Supported concerns regarding agricultural exports.
A22: G/C/M/153 | B22: 46177 | C22: Minutes of the Meeting of the Council for Trade in Goods (27-28 Nov 2025) | D22: CTG | E22: Canada | F22: Concern Raised | G22: Climate & Sustainability | H22: 10.3.2 | I22: Other Climate/Sustainability Measures | L22: MRLs | M22: European Union | N22: =_xlfn.XLOOKUP(O22,'Governance Dimension_Topics'!$C$3:$C$16,'Governance Dimension_Topics'!$B$3:$B$16,"None",0) -> Economic | O22: Market Access & Trade Effects | P22: =_xlfn.XLOOKUP(Q22,'Governance Dimension_Topics'!$C$3:$C$16,'Governance Dimension_Topics'!$B$3:$B$16,"None",0) -> Technical | Q22: Technical Basis | X22: Medium | Y22: Supported concerns regarding trade impacts.
A23: G/C/M/153 | B23: 46177 | C23: Minutes of the Meeting of the Council for Trade in Goods (27-28 Nov 2025) | D23: CTG | E23: European Union | F23: Defence/Explanation | G23: Climate & Sustainability | H23: 10.3.2 | I23: Other Climate/Sustainability Measures | L23: MRLs | M23: European Union | X23: High | Y23: Defended the regulation and underlying risk assessment.
A24: G/C/M/153 | B24: 46177 | C24: Minutes of the Meeting of the Council for Trade in Goods (27-28 Nov 2025) | D24: CTG | E24: European Union | F24: Concern Raised | G24: Industrial Policy & Economic Security | H24: 10.3.8 | I24: Export/Import Controls | L24: Export Controls on Strategic Products | M24: China | N24: =_xlfn.XLOOKUP(O24,'Governance Dimension_Topics'!$C$3:$C$16,'Governance Dimension_Topics'!$B$3:$B$16,"None",0) -> Political Economy | O24: Economic Security & Strategic Autonomy | P24: =_xlfn.XLOOKUP(Q24,'Governance Dimension_Topics'!$C$3:$C$16,'Governance Dimension_Topics'!$B$3:$B$16,"None",0) -> Legal | Q24: WTO Consistency & Legal Interpretation | R24: =_xlfn.XLOOKUP(S24,'Governance Dimension_Topics'!$C$3:$C$16,'Governance Dimension_Topics'!$B$3:$B$16,"None",0) -> Legal | S24: WTO Consistency & Legal Interpretation | X24: High | Y24: Raised concerns regarding China's export control law and strategic product restrictions.
A25: G/C/M/153 | B25: 46177 | C25: Minutes of the Meeting of the Council for Trade in Goods (27-28 Nov 2025) | D25: CTG | E25: India | F25: Concern Raised | G25: Industrial Policy & Economic Security | H25: 10.3.8 | I25: Export/Import Controls | L25: Export Controls on Strategic Products | M25: China | N25: =_xlfn.XLOOKUP(O25,'Governance Dimension_Topics'!$C$3:$C$16,'Governance Dimension_Topics'!$B$3:$B$16,"None",0) -> Economic | O25: Market Access & Trade Effects
A26: G/C/M/153 | B26: 46177 | C26: Minutes of the Meeting of the Council for Trade in Goods (27-28 Nov 2025) | D26: CTG | E26: United States | F26: Concern Raised | G26: Industrial Policy & Economic Security | H26: 10.3.8 | I26: Export/Import Controls | L26: Export Controls on Strategic Products | M26: China | N26: =_xlfn.XLOOKUP(O26,'Governance Dimension_Topics'!$C$3:$C$16,'Governance Dimension_Topics'!$B$3:$B$16,"None",0) -> Legal | O26: Transparency & Due Process
A27: G/C/M/153 | B27: 46177 | C27: Minutes of the Meeting of the Council for Trade in Goods (27-28 Nov 2025) | D27: CTG | E27: Australia | F27: Concern Raised | G27: Industrial Policy & Economic Security | H27: 10.3.8 | I27: Export/Import Controls | L27: Export Controls on Strategic Products | M27: China | N27: =_xlfn.XLOOKUP(O27,'Governance Dimension_Topics'!$C$3:$C$16,'Governance Dimension_Topics'!$B$3:$B$16,"None",0) -> Economic | O27: Market Access & Trade Effects
A28: G/C/M/153 | B28: 46177 | C28: Minutes of the Meeting of the Council for Trade in Goods (27-28 Nov 2025) | D28: CTG | E28: Canada | F28: Concern Raised | G28: Industrial Policy & Economic Security | H28: 10.3.8 | I28: Export/Import Controls | L28: Export Controls on Strategic Products | M28: China | N28: =_xlfn.XLOOKUP(O28,'Governance Dimension_Topics'!$C$3:$C$16,'Governance Dimension_Topics'!$B$3:$B$16,"None",0) -> Economic | O28: Market Access & Trade Effects
A29: G/C/M/153 | B29: 46177 | C29: Minutes of the Meeting of the Council for Trade in Goods (27-28 Nov 2025) | D29: CTG | E29: Norway | F29: Concern Raised | G29: Industrial Policy & Economic Security | H29: 10.3.8 | I29: Export/Import Controls | L29: Export Controls on Strategic Products | M29: China | N29: =_xlfn.XLOOKUP(O29,'Governance Dimension_Topics'!$C$3:$C$16,'Governance Dimension_Topics'!$B$3:$B$16,"None",0) -> Legal | O29: Transparency & Due Process | P29: =_xlfn.XLOOKUP(Q29,'Governance Dimension_Topics'!$C$3:$C$16,'Governance Dimension_Topics'!$B$3:$B$16,"None",0) -> Economic | Q29: Market Access & Trade Effects
A30: G/C/M/153 | B30: 46177 | C30: Minutes of the Meeting of the Council for Trade in Goods (27-28 Nov 2025) | D30: CTG | E30: Switzerland | F30: Concern Raised | G30: Industrial Policy & Economic Security | H30: 10.3.8 | I30: Export/Import Controls | L30: Export Controls on Strategic Products | M30: China | N30: =_xlfn.XLOOKUP(O30,'Governance Dimension_Topics'!$C$3:$C$16,'Governance Dimension_Topics'!$B$3:$B$16,"None",0) -> Legal | O30: WTO Consistency & Legal Interpretation | P30: =_xlfn.XLOOKUP(Q30,'Governance Dimension_Topics'!$C$3:$C$16,'Governance Dimension_Topics'!$B$3:$B$16,"None",0) -> Legal | Q30: Transparency & Due Process | R30: =_xlfn.XLOOKUP(S30,'Governance Dimension_Topics'!$C$3:$C$16,'Governance Dimension_Topics'!$B$3:$B$16,"None",0) -> Economic | S30: Market Access & Trade Effects
A31: G/C/M/153 | B31: 46177 | C31: Minutes of the Meeting of the Council for Trade in Goods (27-28 Nov 2025) | D31: CTG | E31: United Kingdom | F31: Concern Raised | G31: Industrial Policy & Economic Security | H31: 10.3.8 | I31: Export/Import Controls | L31: Export Controls on Strategic Products | M31: China | N31: =_xlfn.XLOOKUP(O31,'Governance Dimension_Topics'!$C$3:$C$16,'Governance Dimension_Topics'!$B$3:$B$16,"None",0) -> Legal | O31: Transparency & Due Process | P31: =_xlfn.XLOOKUP(Q31,'Governance Dimension_Topics'!$C$3:$C$16,'Governance Dimension_Topics'!$B$3:$B$16,"None",0) -> Economic | Q31: Market Access & Trade Effects
A32: G/C/M/153 | B32: 46177 | C32: Minutes of the Meeting of the Council for Trade in Goods (27-28 Nov 2025) | D32: CTG | E32: China | F32: Defence/Explanation | G32: Industrial Policy & Economic Security | H32: 10.3.8 | I32: Export/Import Controls | L32: Export Controls on Strategic Products | M32: China
A33: G/C/M/153 | B33: 46177 | C33: Minutes of the Meeting of the Council for Trade in Goods (27-28 Nov 2025) | D33: CTG | E33: Japan | F33: Concern Raised | G33: Industrial Policy & Economic Security | H33: 10.3.8 | I33: Export/Import Controls | J33: National/Economic Security | L33: Export Controls on Strategic Products | M33: China | N33: =_xlfn.XLOOKUP(O33,'Governance Dimension_Topics'!$C$3:$C$16,'Governance Dimension_Topics'!$B$3:$B$16,"None",0) -> Political Economy | O33: Economic Security & Strategic Autonomy | P33: =_xlfn.XLOOKUP(Q33,'Governance Dimension_Topics'!$C$3:$C$16,'Governance Dimension_Topics'!$B$3:$B$16,"None",0) -> Legal | Q33: Transparency & Due Process | R33: =_xlfn.XLOOKUP(S33,'Governance Dimension_Topics'!$C$3:$C$16,'Governance Dimension_Topics'!$B$3:$B$16,"None",0) -> Legal | S33: WTO Consistency & Legal Interpretation | X33: High | Y33: Raised concerns regarding impacts on supply chains.
A34: G/C/M/153 | B34: 46177 | C34: Minutes of the Meeting of the Council for Trade in Goods (27-28 Nov 2025) | D34: CTG | E34: China | F34: Defence/Explanation | G34: Industrial Policy & Economic Security | H34: 10.3.8 | I34: Export/Import Controls | J34: National/Economic Security | L34: Export Controls on Strategic Products | M34: China | X34: High | Y34: Defended export control measures as legitimate and security-related.
A35: G/C/M/153 | B35: 46177 | C35: Minutes of the Meeting of the Council for Trade in Goods (27-28 Nov 2025) | D35: CTG | E35: Republic of Korea | F35: Concern Raised | G35: Industrial Policy & Economic Security | H35: 10.3.13 | I35: Subsidies | L35: EV Scheme (France) | M35: France | N35: =_xlfn.XLOOKUP(O35,'Governance Dimension_Topics'!$C$3:$C$16,'Governance Dimension_Topics'!$B$3:$B$16,"None",0) -> Political Economy | O35: Economic Security & Strategic Autonomy | P35: =_xlfn.XLOOKUP(Q35,'Governance Dimension_Topics'!$C$3:$C$16,'Governance Dimension_Topics'!$B$3:$B$16,"None",0) -> Legal | Q35: WTO Consistency & Legal Interpretation | X35: High | Y35: Raised concerns regarding French EV subsidy scheme and discriminatory design.
A36: G/C/M/153 | B36: 46177 | C36: Minutes of the Meeting of the Council for Trade in Goods (27-28 Nov 2025) | D36: CTG | E36: European Union | F36: Defence/Explanation | G36: Industrial Policy & Economic Security | H36: 10.3.13 | I36: Subsidies | L36: EV Scheme (France) | M36: France | X36: High | Y36: Defended EV subsidy scheme and environmental criteria.
A37: G/C/M/153 | B37: 46177 | C37: Minutes of the Meeting of the Council for Trade in Goods (27-28 Nov 2025) | D37: CTG | E37: Argentina | F37: Concern Raised | G37: Climate & Sustainability | H37: 10.3.14 | I37: Carbon Measures | L37: EU CBAM | M37: European Union | N37: =_xlfn.XLOOKUP(O37,'Governance Dimension_Topics'!$C$3:$C$16,'Governance Dimension_Topics'!$B$3:$B$16,"None",0) -> Economic | O37: Market Access & Trade Effects | P37: =_xlfn.XLOOKUP(Q37,'Governance Dimension_Topics'!$C$3:$C$16,'Governance Dimension_Topics'!$B$3:$B$16,"None",0) -> Legal | Q37: WTO Consistency & Legal Interpretation | R37: =_xlfn.XLOOKUP(S37,'Governance Dimension_Topics'!$C$3:$C$16,'Governance Dimension_Topics'!$B$3:$B$16,"None",0) -> Technical | S37: Technical Basis | X37: High | Y37: Concern over CBAM trade effects on developing country exports and climate-trade balance.
A38: G/C/M/153 | B38: 46177 | C38: Minutes of the Meeting of the Council for Trade in Goods (27-28 Nov 2025) | D38: CTG | E38: Brazil | F38: Concern Raised | G38: Climate & Sustainability | H38: 10.3.14 | I38: Carbon Measures | L38: EU CBAM | M38: European Union | N38: =_xlfn.XLOOKUP(O38,'Governance Dimension_Topics'!$C$3:$C$16,'Governance Dimension_Topics'!$B$3:$B$16,"None",0) -> Development | O38: Equity & Just Transition | P38: =_xlfn.XLOOKUP(Q38,'Governance Dimension_Topics'!$C$3:$C$16,'Governance Dimension_Topics'!$B$3:$B$16,"None",0) -> Legal | Q38: WTO Consistency & Legal Interpretation | R38: =_xlfn.XLOOKUP(S38,'Governance Dimension_Topics'!$C$3:$C$16,'Governance Dimension_Topics'!$B$3:$B$16,"None",0) -> Development | S38: Policy Space | X38: High | Y38: Argued CBAM disregards CBDR principles and unfairly shifts burden to developing countries.
A39: G/C/M/153 | B39: 46177 | C39: Minutes of the Meeting of the Council for Trade in Goods (27-28 Nov 2025) | D39: CTG | E39: China | F39: Concern Raised | G39: Climate & Sustainability | H39: 10.3.14 | I39: Carbon Measures | L39: EU CBAM | M39: European Union | N39: =_xlfn.XLOOKUP(O39,'Governance Dimension_Topics'!$C$3:$C$16,'Governance Dimension_Topics'!$B$3:$B$16,"None",0) -> Legal | O39: WTO Consistency & Legal Interpretation | P39: =_xlfn.XLOOKUP(Q39,'Governance Dimension_Topics'!$C$3:$C$16,'Governance Dimension_Topics'!$B$3:$B$16,"None",0) -> Development | Q39: Equity & Just Transition | R39: =_xlfn.XLOOKUP(S39,'Governance Dimension_Topics'!$C$3:$C$16,'Governance Dimension_Topics'!$B$3:$B$16,"None",0) -> Economic | S39: Market Access & Trade Effects | T39: =_xlfn.XLOOKUP(U39,'Governance Dimension_Topics'!$C$3:$C$16,'Governance Dimension_Topics'!$B$3:$B$16,"None",0) -> Regulatory | U39: Interoperability & Equivalence | X39: High | Y39: Questioned compatibility of CBAM with multilateral trade rules and non-discrimination.
A40: G/C/M/153 | B40: 46177 | C40: Minutes of the Meeting of the Council for Trade in Goods (27-28 Nov 2025) | D40: CTG | E40: Indonesia | F40: Concern Raised | G40: Climate & Sustainability | H40: 10.3.14 | I40: Carbon Measures | L40: EU CBAM | M40: European Union | N40: =_xlfn.XLOOKUP(O40,'Governance Dimension_Topics'!$C$3:$C$16,'Governance Dimension_Topics'!$B$3:$B$16,"None",0) -> Development | O40: Equity & Just Transition | P40: =_xlfn.XLOOKUP(Q40,'Governance Dimension_Topics'!$C$3:$C$16,'Governance Dimension_Topics'!$B$3:$B$16,"None",0) -> Legal | Q40: WTO Consistency & Legal Interpretation | R40: =_xlfn.XLOOKUP(S40,'Governance Dimension_Topics'!$C$3:$C$16,'Governance Dimension_Topics'!$B$3:$B$16,"None",0) -> Economic | S40: Market Access & Trade Effects | T40: =_xlfn.XLOOKUP(U40,'Governance Dimension_Topics'!$C$3:$C$16,'Governance Dimension_Topics'!$B$3:$B$16,"None",0) -> Regulatory | U40: Interoperability & Equivalence | X40: High | Y40: Raised concerns regarding impacts on industrialization and policy autonomy.
A41: G/C/M/153 | B41: 46177 | C41: Minutes of the Meeting of the Council for Trade in Goods (27-28 Nov 2025) | D41: CTG | E41: Thailand | F41: Concern Raised | G41: Climate & Sustainability | H41: 10.3.14 | I41: Carbon Measures | L41: EU CBAM | M41: European Union | N41: =_xlfn.XLOOKUP(O41,'Governance Dimension_Topics'!$C$3:$C$16,'Governance Dimension_Topics'!$B$3:$B$16,"None",0) -> Economic | O41: Compliance Costs | P41: =_xlfn.XLOOKUP(Q41,'Governance Dimension_Topics'!$C$3:$C$16,'Governance Dimension_Topics'!$B$3:$B$16,"None",0) -> Technical | Q41: MRV methodologies | R41: =_xlfn.XLOOKUP(S41,'Governance Dimension_Topics'!$C$3:$C$16,'Governance Dimension_Topics'!$B$3:$B$16,"None",0) -> Technical | S41: MRV methodologies | X41: High | Y41: Highlighted reporting and compliance burdens associated with CBAM.
A42: G/C/M/153 | B42: 46177 | C42: Minutes of the Meeting of the Council for Trade in Goods (27-28 Nov 2025) | D42: CTG | E42: Thailand | F42: Proposal/Recommendation | G42: Climate & Sustainability | H42: 10.3.14 | I42: Other Climate/Sustainability Measures | L42: EU CBAM | M42: European Union | N42: =_xlfn.XLOOKUP(O42,'Governance Dimension_Topics'!$C$3:$C$16,'Governance Dimension_Topics'!$B$3:$B$16,"None",0) -> Regulatory | O42: Interoperability & Equivalence
A43: G/C/M/153 | B43: 46177 | C43: Minutes of the Meeting of the Council for Trade in Goods (27-28 Nov 2025) | D43: CTG | E43: India | F43: Concern Raised | G43: Climate & Sustainability | H43: 10.3.14 | I43: Carbon Measures | L43: EU CBAM | M43: European Union | N43: =_xlfn.XLOOKUP(O43,'Governance Dimension_Topics'!$C$3:$C$16,'Governance Dimension_Topics'!$B$3:$B$16,"None",0) -> Development | O43: Equity & Just Transition | P43: =_xlfn.XLOOKUP(Q43,'Governance Dimension_Topics'!$C$3:$C$16,'Governance Dimension_Topics'!$B$3:$B$16,"None",0) -> Economic | Q43: Market Access & Trade Effects | R43: =_xlfn.XLOOKUP(S43,'Governance Dimension_Topics'!$C$3:$C$16,'Governance Dimension_Topics'!$B$3:$B$16,"None",0) -> Legal | S43: WTO Consistency & Legal Interpretation
A44: G/C/M/153 | B44: 46177 | C44: Minutes of the Meeting of the Council for Trade in Goods (27-28 Nov 2025) | D44: CTG | E44: Chinese Taipei | F44: Proposal/Recommendation | G44: Climate & Sustainability | H44: 10.3.14 | I44: Other Climate/Sustainability Measures | L44: EU CBAM | M44: European Union | N44: =_xlfn.XLOOKUP(O44,'Governance Dimension_Topics'!$C$3:$C$16,'Governance Dimension_Topics'!$B$3:$B$16,"None",0) -> Regulatory | O44: Interoperability & Equivalence | P44: =_xlfn.XLOOKUP(Q44,'Governance Dimension_Topics'!$C$3:$C$16,'Governance Dimension_Topics'!$B$3:$B$16,"None",0) -> Technical | Q44: MRV methodologies
A45: G/C/M/153 | B45: 46177 | C45: Minutes of the Meeting of the Council for Trade in Goods (27-28 Nov 2025) | D45: CTG | E45: Türkiye | F45: Concern Raised | G45: Climate & Sustainability | H45: 10.3.14 | I45: Carbon Measures | L45: EU CBAM | M45: European Union | N45: =_xlfn.XLOOKUP(O45,'Governance Dimension_Topics'!$C$3:$C$16,'Governance Dimension_Topics'!$B$3:$B$16,"None",0) -> Economic | O45: Compliance Costs | P45: =_xlfn.XLOOKUP(Q45,'Governance Dimension_Topics'!$C$3:$C$16,'Governance Dimension_Topics'!$B$3:$B$16,"None",0) -> Regulatory | Q45: Interoperability & Equivalence | R45: =_xlfn.XLOOKUP(S45,'Governance Dimension_Topics'!$C$3:$C$16,'Governance Dimension_Topics'!$B$3:$B$16,"None",0) -> Legal | S45: WTO Consistency & Legal Interpretation
A46: G/C/M/153 | B46: 46177 | C46: Minutes of the Meeting of the Council for Trade in Goods (27-28 Nov 2025) | D46: CTG | E46: Japan | F46: Concern Raised | G46: Climate & Sustainability | H46: 10.3.14 | I46: Carbon Measures | L46: EU CBAM | M46: European Union | N46: =_xlfn.XLOOKUP(O46,'Governance Dimension_Topics'!$C$3:$C$16,'Governance Dimension_Topics'!$B$3:$B$16,"None",0) -> Regulatory | O46: Interoperability & Equivalence | P46: =_xlfn.XLOOKUP(Q46,'Governance Dimension_Topics'!$C$3:$C$16,'Governance Dimension_Topics'!$B$3:$B$16,"None",0) -> Economic | Q46: Compliance Costs | R46: =_xlfn.XLOOKUP(S46,'Governance Dimension_Topics'!$C$3:$C$16,'Governance Dimension_Topics'!$B$3:$B$16,"None",0) -> Technical | S46: MRV methodologies
A47: G/C/M/153 | B47: 46177 | C47: Minutes of the Meeting of the Council for Trade in Goods (27-28 Nov 2025) | D47: CTG | E47: Japan | F47: Proposal/Recommendation | G47: Climate & Sustainability | H47: 10.3.14 | I47: Other Climate/Sustainability Measures | L47: EU CBAM | M47: European Union | N47: =_xlfn.XLOOKUP(O47,'Governance Dimension_Topics'!$C$3:$C$16,'Governance Dimension_Topics'!$B$3:$B$16,"None",0) -> Regulatory | O47: Interoperability & Equivalence
A48: G/C/M/153 | B48: 46177 | C48: Minutes of the Meeting of the Council for Trade in Goods (27-28 Nov 2025) | D48: CTG | E48: Korea | F48: Concern Raised | G48: Climate & Sustainability | H48: 10.3.14 | I48: Carbon Measures | L48: EU CBAM | M48: European Union | N48: =_xlfn.XLOOKUP(O48,'Governance Dimension_Topics'!$C$3:$C$16,'Governance Dimension_Topics'!$B$3:$B$16,"None",0) -> Economic | O48: Compliance Costs | P48: =_xlfn.XLOOKUP(Q48,'Governance Dimension_Topics'!$C$3:$C$16,'Governance Dimension_Topics'!$B$3:$B$16,"None",0) -> Economic | Q48: Market Access & Trade Effects
A49: G/C/M/153 | B49: 46177 | C49: Minutes of the Meeting of the Council for Trade in Goods (27-28 Nov 2025) | D49: CTG | E49: European Union | F49: Defence/Explanation | G49: Climate & Sustainability | H49: 10.3.14 | I49: Other Climate/Sustainability Measures | L49: EU CBAM | M49: European Union | X49: High | Y49: Defended CBAM as climate measure designed to address carbon leakage and ensure equivalent carbon pricing.
A50: G/C/M/153 | B50: 46177 | C50: Minutes of the Meeting of the Council for Trade in Goods (27-28 Nov 2025) | D50: CTG | E50: Argentina | F50: Concern Raised | G50: Climate & Sustainability | H50: 10.3.15 | I50: Deforestation & Biodiversity | L50: EU DR | M50: European Union | N50: =_xlfn.XLOOKUP(O50,'Governance Dimension_Topics'!$C$3:$C$16,'Governance Dimension_Topics'!$B$3:$B$16,"None",0) -> Economic | O50: Market Access & Trade Effects | P50: =_xlfn.XLOOKUP(Q50,'Governance Dimension_Topics'!$C$3:$C$16,'Governance Dimension_Topics'!$B$3:$B$16,"None",0) -> Development | Q50: Policy Space | R50: =_xlfn.XLOOKUP(S50,'Governance Dimension_Topics'!$C$3:$C$16,'Governance Dimension_Topics'!$B$3:$B$16,"None",0) -> Legal | S50: WTO Consistency & Legal Interpretation | X50: High | Y50: Raised concerns regarding market access implications for agricultural exports.
A51: G/C/M/153 | B51: 46177 | C51: Minutes of the Meeting of the Council for Trade in Goods (27-28 Nov 2025) | D51: CTG | E51: Brazil | F51: Concern Raised | G51: Climate & Sustainability | H51: 10.3.15 | I51: Deforestation & Biodiversity | L51: EU DR | M51: European Union | N51: =_xlfn.XLOOKUP(O51,'Governance Dimension_Topics'!$C$3:$C$16,'Governance Dimension_Topics'!$B$3:$B$16,"None",0) -> Legal | O51: WTO Consistency & Legal Interpretation | X51: High | Y51: Argued EUDR imposes EU standards on foreign producers and production systems.
A52: G/C/M/153 | B52: 46177 | C52: Minutes of the Meeting of the Council for Trade in Goods (27-28 Nov 2025) | D52: CTG | E52: Ecuador | F52: Concern Raised | G52: Climate & Sustainability | H52: 10.3.15 | I52: Deforestation & Biodiversity | L52: EU DR | M52: European Union | N52: =_xlfn.XLOOKUP(O52,'Governance Dimension_Topics'!$C$3:$C$16,'Governance Dimension_Topics'!$B$3:$B$16,"None",0) -> Development | O52: Capacity Constraints | P52: =_xlfn.XLOOKUP(Q52,'Governance Dimension_Topics'!$C$3:$C$16,'Governance Dimension_Topics'!$B$3:$B$16,"None",0) -> Regulatory | Q52: Interoperability & Equivalence | R52: =_xlfn.XLOOKUP(S52,'Governance Dimension_Topics'!$C$3:$C$16,'Governance Dimension_Topics'!$B$3:$B$16,"None",0) -> Technical | S52: MRV methodologies | X52: High | Y52: Highlighted implementation challenges for developing country producers.
A53: G/C/M/153 | B53: 46177 | C53: Minutes of the Meeting of the Council for Trade in Goods (27-28 Nov 2025) | D53: CTG | E53: Indonesia | F53: Concern Raised | G53: Climate & Sustainability | H53: 10.3.15 | I53: Deforestation & Biodiversity | L53: EU DR | M53: European Union | N53: =_xlfn.XLOOKUP(O53,'Governance Dimension_Topics'!$C$3:$C$16,'Governance Dimension_Topics'!$B$3:$B$16,"None",0) -> Technical | O53: MRV methodologies | P53: =_xlfn.XLOOKUP(Q53,'Governance Dimension_Topics'!$C$3:$C$16,'Governance Dimension_Topics'!$B$3:$B$16,"None",0) -> Legal | Q53: WTO Consistency & Legal Interpretation | R53: =_xlfn.XLOOKUP(S53,'Governance Dimension_Topics'!$C$3:$C$16,'Governance Dimension_Topics'!$B$3:$B$16,"None",0) -> Regulatory | S53: Interoperability & Equivalence | X53: High | Y53: Raised concerns over traceability requirements and compliance systems.
A54: G/C/M/153 | B54: 46177 | C54: Minutes of the Meeting of the Council for Trade in Goods (27-28 Nov 2025) | D54: CTG | E54: Paraguay | F54: Concern Raised | G54: Climate & Sustainability | H54: 10.3.15 | I54: Deforestation & Biodiversity | L54: EU DR | M54: European Union | N54: =_xlfn.XLOOKUP(O54,'Governance Dimension_Topics'!$C$3:$C$16,'Governance Dimension_Topics'!$B$3:$B$16,"None",0) -> Technical | O54: MRV methodologies | P54: =_xlfn.XLOOKUP(Q54,'Governance Dimension_Topics'!$C$3:$C$16,'Governance Dimension_Topics'!$B$3:$B$16,"None",0) -> Economic | Q54: Compliance Costs | R54: =_xlfn.XLOOKUP(S54,'Governance Dimension_Topics'!$C$3:$C$16,'Governance Dimension_Topics'!$B$3:$B$16,"None",0) -> Development | S54: Equity & Just Transition | X54: High | Y54: Questioned certification and verification requirements.
A55: G/C/M/153 | B55: 46177 | C55: Minutes of the Meeting of the Council for Trade in Goods (27-28 Nov 2025) | D55: CTG | E55: India | F55: Concern Raised | G55: Climate & Sustainability | H55: 10.3.15 | I55: Deforestation & Biodiversity | L55: EU DR | M55: European Union | N55: =_xlfn.XLOOKUP(O55,'Governance Dimension_Topics'!$C$3:$C$16,'Governance Dimension_Topics'!$B$3:$B$16,"None",0) -> Development | O55: Equity & Just Transition | P55: =_xlfn.XLOOKUP(Q55,'Governance Dimension_Topics'!$C$3:$C$16,'Governance Dimension_Topics'!$B$3:$B$16,"None",0) -> Legal | Q55: WTO Consistency & Legal Interpretation
A56: G/C/M/153 | B56: 46177 | C56: Minutes of the Meeting of the Council for Trade in Goods (27-28 Nov 2025) | D56: CTG | E56: Peru | F56: Concern Raised | G56: Climate & Sustainability | H56: 10.3.15 | I56: Deforestation & Biodiversity | L56: EU DR | M56: European Union | N56: =_xlfn.XLOOKUP(O56,'Governance Dimension_Topics'!$C$3:$C$16,'Governance Dimension_Topics'!$B$3:$B$16,"None",0) -> Legal | O56: WTO Consistency & Legal Interpretation | P56: =_xlfn.XLOOKUP(Q56,'Governance Dimension_Topics'!$C$3:$C$16,'Governance Dimension_Topics'!$B$3:$B$16,"None",0) -> Development | Q56: Equity & Just Transition | R56: =_xlfn.XLOOKUP(S56,'Governance Dimension_Topics'!$C$3:$C$16,'Governance Dimension_Topics'!$B$3:$B$16,"None",0) -> Development | S56: Policy Space
A57: G/C/M/153 | B57: 46177 | C57: Minutes of the Meeting of the Council for Trade in Goods (27-28 Nov 2025) | D57: CTG | E57: United States | F57: Concern Raised | G57: Climate & Sustainability | H57: 10.3.15 | I57: Deforestation & Biodiversity | L57: EU DR | M57: European Union | N57: =_xlfn.XLOOKUP(O57,'Governance Dimension_Topics'!$C$3:$C$16,'Governance Dimension_Topics'!$B$3:$B$16,"None",0) -> Economic | O57: Market Access & Trade Effects
A58: G/C/M/153 | B58: 46177 | C58: Minutes of the Meeting of the Council for Trade in Goods (27-28 Nov 2025) | D58: CTG | E58: Türkiye | F58: Concern Raised | G58: Climate & Sustainability | H58: 10.3.15 | I58: Deforestation & Biodiversity | L58: EU DR | M58: European Union | N58: =_xlfn.XLOOKUP(O58,'Governance Dimension_Topics'!$C$3:$C$16,'Governance Dimension_Topics'!$B$3:$B$16,"None",0) -> Economic | O58: Market Access & Trade Effects | P58: =_xlfn.XLOOKUP(Q58,'Governance Dimension_Topics'!$C$3:$C$16,'Governance Dimension_Topics'!$B$3:$B$16,"None",0) -> Economic | Q58: Compliance Costs
A59: G/C/M/153 | B59: 46177 | C59: Minutes of the Meeting of the Council for Trade in Goods (27-28 Nov 2025) | D59: CTG | E59: Colombia | F59: Concern Raised | G59: Climate & Sustainability | H59: 10.3.15 | I59: Deforestation & Biodiversity | L59: EU DR | M59: European Union | N59: =_xlfn.XLOOKUP(O59,'Governance Dimension_Topics'!$C$3:$C$16,'Governance Dimension_Topics'!$B$3:$B$16,"None",0) -> Economic | O59: Compliance Costs | P59: =_xlfn.XLOOKUP(Q59,'Governance Dimension_Topics'!$C$3:$C$16,'Governance Dimension_Topics'!$B$3:$B$16,"None",0) -> Technical | Q59: MRV methodologies
A60: G/C/M/153 | B60: 46177 | C60: Minutes of the Meeting of the Council for Trade in Goods (27-28 Nov 2025) | D60: CTG | E60: New Zealand | F60: Concern Raised | G60: Climate & Sustainability | H60: 10.3.15 | I60: Deforestation & Biodiversity | L60: EU DR | M60: European Union | N60: =_xlfn.XLOOKUP(O60,'Governance Dimension_Topics'!$C$3:$C$16,'Governance Dimension_Topics'!$B$3:$B$16,"None",0) -> Legal | O60: WTO Consistency & Legal Interpretation | P60: =_xlfn.XLOOKUP(Q60,'Governance Dimension_Topics'!$C$3:$C$16,'Governance Dimension_Topics'!$B$3:$B$16,"None",0) -> Economic | Q60: Compliance Costs
A61: G/C/M/153 | B61: 46177 | C61: Minutes of the Meeting of the Council for Trade in Goods (27-28 Nov 2025) | D61: CTG | E61: Australia | F61: Concern Raised | G61: Climate & Sustainability | H61: 10.3.15 | I61: Deforestation & Biodiversity | L61: EU DR | M61: European Union | N61: =_xlfn.XLOOKUP(O61,'Governance Dimension_Topics'!$C$3:$C$16,'Governance Dimension_Topics'!$B$3:$B$16,"None",0) -> Economic | O61: Market Access & Trade Effects | P61: =_xlfn.XLOOKUP(Q61,'Governance Dimension_Topics'!$C$3:$C$16,'Governance Dimension_Topics'!$B$3:$B$16,"None",0) -> Economic | Q61: Compliance Costs
A62: G/C/M/153 | B62: 46177 | C62: Minutes of the Meeting of the Council for Trade in Goods (27-28 Nov 2025) | D62: CTG | E62: European Union | F62: Defence/Explanation | G62: Climate & Sustainability | H62: 10.3.15 | I62: Deforestation & Biodiversity | L62: EU DR | M62: European Union
A63: G/C/M/153 | B63: 46177 | C63: Minutes of the Meeting of the Council for Trade in Goods (27-28 Nov 2025) | D63: CTG | E63: Russian Federation | F63: Concern Raised | G63: Climate & Sustainability | H63: 10.3.15 | I63: Deforestation & Biodiversity | L63: EU DR | M63: European Union | N63: =_xlfn.XLOOKUP(O63,'Governance Dimension_Topics'!$C$3:$C$16,'Governance Dimension_Topics'!$B$3:$B$16,"None",0) -> Regulatory | O63: Interoperability & Equivalence | P63: =_xlfn.XLOOKUP(Q63,'Governance Dimension_Topics'!$C$3:$C$16,'Governance Dimension_Topics'!$B$3:$B$16,"None",0) -> Legal | Q63: WTO Consistency & Legal Interpretation | R63: =_xlfn.XLOOKUP(S63,'Governance Dimension_Topics'!$C$3:$C$16,'Governance Dimension_Topics'!$B$3:$B$16,"None",0) -> Legal | S63: WTO Consistency & Legal Interpretation | X63: High | Y63: Criticized unilateral environmental measures creating fragmented trade regimes.
A64: G/C/M/153 | B64: 46177 | C64: Minutes of the Meeting of the Council for Trade in Goods (27-28 Nov 2025) | D64: CTG | E64: Thailand | F64: Concern Raised | G64: Climate & Sustainability | H64: 10.3.15 | I64: Deforestation & Biodiversity | L64: EU DR | M64: European Union | N64: Development | O64: Capacity Constraints | X64: Medium | Y64: Emphasized need for support and transition assistance.
A65: G/C/M/153 | B65: 46177 | C65: Minutes of the Meeting of the Council for Trade in Goods (27-28 Nov 2025) | D65: CTG | E65: European Union | F65: Defence/Explanation | G65: Climate & Sustainability | H65: 10.3.15 | I65: Deforestation & Biodiversity | L65: EU DR | M65: European Union | X65: High | Y65: Defended EUDR as environmental measure aimed at reducing global deforestation and improving supply-chain sustainability.
A66: G/C/M/153 | B66: 46177 | C66: Minutes of the Meeting of the Council for Trade in Goods (27-28 Nov 2025) | D66: CTG | E66: China | F66: Concern Raised | G66: Industrial Policy & Economic Security | H66: 10.3.17 | I66: National/Economic Security | J66: National/Economic Security | L66: US Reciprocal Tariffs | M66: United States | N66: =_xlfn.XLOOKUP(O66,'Governance Dimension_Topics'!$C$3:$C$16,'Governance Dimension_Topics'!$B$3:$B$16,"None",0) -> Political Economy | O66: Economic Security & Strategic Autonomy | P66: =_xlfn.XLOOKUP(Q66,'Governance Dimension_Topics'!$C$3:$C$16,'Governance Dimension_Topics'!$B$3:$B$16,"None",0) -> Legal | Q66: WTO Consistency & Legal Interpretation | R66: =_xlfn.XLOOKUP(S66,'Governance Dimension_Topics'!$C$3:$C$16,'Governance Dimension_Topics'!$B$3:$B$16,"None",0) -> Economic | S66: Market Access & Trade Effects | X66: High | Y66: Argued US reciprocal tariffs reverse tariff liberalization, violate MFN, disproportionately affect developing countries, and disrupt global supply chains.
A67: G/C/M/153 | B67: 46177 | C67: Minutes of the Meeting of the Council for Trade in Goods (27-28 Nov 2025) | D67: CTG | E67: Venezuela | F67: Concern Raised | G67: Industrial Policy & Economic Security | H67: 10.3.17 | I67: National/Economic Security | J67: National/Economic Security | L67: US Reciprocal Tariffs | M67: United States | N67: =_xlfn.XLOOKUP(O67,'Governance Dimension_Topics'!$C$3:$C$16,'Governance Dimension_Topics'!$B$3:$B$16,"None",0) -> Development | O67: Policy Space | X67: High | Y67: Supported China and criticized reciprocal and secondary tariffs as protectionist and inconsistent with WTO rules.
A68: G/C/M/153 | B68: 46177 | C68: Minutes of the Meeting of the Council for Trade in Goods (27-28 Nov 2025) | D68: CTG | E68: Canada | F68: Concern Raised | G68: Industrial Policy & Economic Security | H68: 10.3.20 | I68: Export/Import Controls | L68: Comm. Balance Mechanism and Import Restrictions | M68: Indonesia | N68: Economic | O68: Market Access & Trade Effects | X68: Medium | Y68: Raised concerns regarding Indonesia's commodity balance mechanism and import restrictions.
A69: G/C/M/153 | B69: 46177 | C69: Minutes of the Meeting of the Council for Trade in Goods (27-28 Nov 2025) | D69: CTG | E69: Japan | F69: Concern Raised | G69: Industrial Policy & Economic Security | H69: 10.3.20 | I69: Export/Import Controls | L69: Comm. Balance Mechanism and Import Restrictions | M69: Indonesia | N69: =_xlfn.XLOOKUP(O69,'Governance Dimension_Topics'!$C$3:$C$16,'Governance Dimension_Topics'!$B$3:$B$16,"None",0) -> Legal | O69: Transparency & Due Process | P69: =_xlfn.XLOOKUP(Q69,'Governance Dimension_Topics'!$C$3:$C$16,'Governance Dimension_Topics'!$B$3:$B$16,"None",0) -> Economic | Q69: Market Access & Trade Effects | X69: Medium | Y69: Expressed concerns regarding import licensing and commodity balance administration.
A70: G/C/M/153 | B70: 46177 | C70: Minutes of the Meeting of the Council for Trade in Goods (27-28 Nov 2025) | D70: CTG | E70: New Zealand | F70: Concern Raised | G70: Industrial Policy & Economic Security | H70: 10.3.20 | I70: Export/Import Controls | L70: Comm. Balance Mechanism and Import Restrictions | M70: Indonesia | N70: Economic | O70: Market Access & Trade Effects | P70: =_xlfn.XLOOKUP(Q70,'Governance Dimension_Topics'!$C$3:$C$16,'Governance Dimension_Topics'!$B$3:$B$16,"None",0) -> Legal | Q70: Transparency & Due Process | X70: Medium | Y70: Supported concerns regarding restrictive import policies.
A71: G/C/M/153 | B71: 46177 | C71: Minutes of the Meeting of the Council for Trade in Goods (27-28 Nov 2025) | D71: CTG | E71: United Kingdom | F71: Concern Raised | G71: Industrial Policy & Economic Security | H71: 10.3.20 | I71: Export/Import Controls | L71: Comm. Balance Mechanism and Import Restrictions | M71: Indonesia | N71: =_xlfn.XLOOKUP(O71,'Governance Dimension_Topics'!$C$3:$C$16,'Governance Dimension_Topics'!$B$3:$B$16,"None",0) -> Economic | O71: Market Access & Trade Effects | P71: =_xlfn.XLOOKUP(Q71,'Governance Dimension_Topics'!$C$3:$C$16,'Governance Dimension_Topics'!$B$3:$B$16,"None",0) -> Legal | Q71: Transparency & Due Process | X71: Medium | Y71: Raised concerns regarding trade-restrictive effects of Indonesia's mechanism.
A72: G/C/M/153 | B72: 46177 | C72: Minutes of the Meeting of the Council for Trade in Goods (27-28 Nov 2025) | D72: CTG | E72: India | F72: Concern Raised | G72: Industrial Policy & Economic Security | H72: 10.3.20 | I72: Export/Import Controls | L72: Comm. Balance Mechanism and Import Restrictions | M72: Indonesia | N72: =_xlfn.XLOOKUP(O72,'Governance Dimension_Topics'!$C$3:$C$16,'Governance Dimension_Topics'!$B$3:$B$16,"None",0) -> Economic | O72: Market Access & Trade Effects
A73: G/C/M/153 | B73: 46177 | C73: Minutes of the Meeting of the Council for Trade in Goods (27-28 Nov 2025) | D73: CTG | E73: Korea | F73: Concern Raised | G73: Industrial Policy & Economic Security | H73: 10.3.20 | I73: Export/Import Controls | L73: Comm. Balance Mechanism and Import Restrictions | M73: Indonesia | N73: =_xlfn.XLOOKUP(O73,'Governance Dimension_Topics'!$C$3:$C$16,'Governance Dimension_Topics'!$B$3:$B$16,"None",0) -> Economic | O73: Market Access & Trade Effects | P73: =_xlfn.XLOOKUP(Q73,'Governance Dimension_Topics'!$C$3:$C$16,'Governance Dimension_Topics'!$B$3:$B$16,"None",0) -> Legal | Q73: WTO Consistency & Legal Interpretation
A74: G/C/M/153 | B74: 46177 | C74: Minutes of the Meeting of the Council for Trade in Goods (27-28 Nov 2025) | D74: CTG | E74: Indonesia | F74: Defence/Explanation | G74: Industrial Policy & Economic Security | H74: 10.3.20 | I74: Export/Import Controls | L74: Comm. Balance Mechanism and Import Restrictions | M74: Indonesia | X74: Medium | Y74: Defended the commodity balance mechanism and import management measures.
A75: G/C/M/153 | B75: 46177 | C75: Minutes of the Meeting of the Council for Trade in Goods (27-28 Nov 2025) | D75: CTG | E75: Russian Federation | F75: Concern Raised | G75: Industrial Policy & Economic Security | H75: 10.3.21 | I75: National/Economic Security | L75: Unilateral Measures Against Russia | M75: Multiple Members | N75: =_xlfn.XLOOKUP(O75,'Governance Dimension_Topics'!$C$3:$C$16,'Governance Dimension_Topics'!$B$3:$B$16,"None",0) -> Political Economy | O75: Economic Security & Strategic Autonomy | P75: =_xlfn.XLOOKUP(Q75,'Governance Dimension_Topics'!$C$3:$C$16,'Governance Dimension_Topics'!$B$3:$B$16,"None",0) -> Legal | Q75: WTO Consistency & Legal Interpretation | R75: =_xlfn.XLOOKUP(S75,'Governance Dimension_Topics'!$C$3:$C$16,'Governance Dimension_Topics'!$B$3:$B$16,"None",0) -> Economic | S75: Market Access & Trade Effects | X75: High | Y75: Challenged sanctions and unilateral trade restrictive measures imposed by Australia, Canada, EU, Japan, New Zealand, Switzerland, UK and US.
A76: G/C/M/153 | B76: 46177 | C76: Minutes of the Meeting of the Council for Trade in Goods (27-28 Nov 2025) | D76: CTG | E76: European Union | F76: Defence/Explanation | G76: Industrial Policy & Economic Security | H76: 10.3.21 | I76: National/Economic Security | L76: Unilateral Measures Against Russia | M76: European Union | X76: High | Y76: Defended measures adopted in response to Russia's actions in Ukraine.
A77: G/C/M/153 | B77: 46177 | C77: Minutes of the Meeting of the Council for Trade in Goods (27-28 Nov 2025) | D77: CTG | E77: Ukraine | F77: Defence/Explanation | G77: Industrial Policy & Economic Security | H77: 10.3.21 | I77: National/Economic Security | L77: Unilateral Measures Against Russia | M77: European Union
A78: G/C/M/153 | B78: 46177 | C78: Minutes of the Meeting of the Council for Trade in Goods (27-28 Nov 2025) | D78: CTG | E78: Australia | F78: Defence/Explanation | G78: Industrial Policy & Economic Security | H78: 10.3.21 | I78: National/Economic Security | L78: Unilateral Measures Against Russia | M78: Australia
A79: G/C/M/153 | B79: 46177 | C79: Minutes of the Meeting of the Council for Trade in Goods (27-28 Nov 2025) | D79: CTG | E79: Switzerland | F79: Defence/Explanation | G79: Industrial Policy & Economic Security | H79: 10.3.21 | I79: National/Economic Security | L79: Unilateral Measures Against Russia | M79: Switzerland
A80: G/C/M/153 | B80: 46177 | C80: Minutes of the Meeting of the Council for Trade in Goods (27-28 Nov 2025) | D80: CTG | E80: United Kingdom | F80: Defence/Explanation | G80: Industrial Policy & Economic Security | H80: 10.3.21 | I80: National/Economic Security | L80: Unilateral Measures Against Russia | M80: United Kingdom | X80: High | Y80: Justified sanctions and trade restrictions linked to the conflict in Ukraine.
A81: G/C/M/153 | B81: 46177 | C81: Minutes of the Meeting of the Council for Trade in Goods (27-28 Nov 2025) | D81: CTG | E81: New Zealand | F81: Defence/Explanation | G81: Industrial Policy & Economic Security | H81: 10.3.21 | I81: National/Economic Security | L81: Unilateral Measures Against Russia | M81: New Zealand
A82: G/C/M/153 | B82: 46177 | C82: Minutes of the Meeting of the Council for Trade in Goods (27-28 Nov 2025) | D82: CTG | E82: Canada | F82: Defence/Explanation | G82: Industrial Policy & Economic Security | H82: 10.3.21 | I82: National/Economic Security | L82: Unilateral Measures Against Russia | M82: Canada | X82: High | Y82: Defended measures as necessary responses to Russia's aggression.
A83: G/C/M/153 | B83: 46177 | C83: Minutes of the Meeting of the Council for Trade in Goods (27-28 Nov 2025) | D83: CTG | E83: Japan | F83: Defence/Explanation | G83: Industrial Policy & Economic Security | H83: 10.3.21 | I83: National/Economic Security | L83: Unilateral Measures Against Russia | M83: Japan | X83: High | Y83: Defended sanctions while emphasizing food security and humanitarian carve-outs.
A84: G/C/M/153 | B84: 46177 | C84: Minutes of the Meeting of the Council for Trade in Goods (27-28 Nov 2025) | D84: CTG | E84: Japan | F84: Concern Raised | G84: Industrial Policy & Economic Security | H84: 10.3.23 | I84: Government Procurement | L84: Chinese Government Procurement | M84: China | N84: =_xlfn.XLOOKUP(O84,'Governance Dimension_Topics'!$C$3:$C$16,'Governance Dimension_Topics'!$B$3:$B$16,"None",0) -> Economic | O84: Market Access & Trade Effects | P84: =_xlfn.XLOOKUP(Q84,'Governance Dimension_Topics'!$C$3:$C$16,'Governance Dimension_Topics'!$B$3:$B$16,"None",0) -> Legal | Q84: WTO Consistency & Legal Interpretation
A85: G/C/M/153 | B85: 46177 | C85: Minutes of the Meeting of the Council for Trade in Goods (27-28 Nov 2025) | D85: CTG | E85: China | F85: Defence/Explanation | G85: Industrial Policy & Economic Security | H85: 10.3.23 | I85: Government Procurement | L85: Chinese Government Procurement | M85: China
A86: G/C/M/153 | B86: 46177 | C86: Minutes of the Meeting of the Council for Trade in Goods (27-28 Nov 2025) | D86: CTG | E86: China | F86: Concern Raised | G86: Industrial Policy & Economic Security | H86: 10.3.24 | I86: National/Economic Security | J86: Export/Import Controls | L86: Disruptive Policy Measures on Semiconductors | M86: United States | N86: =_xlfn.XLOOKUP(O86,'Governance Dimension_Topics'!$C$3:$C$16,'Governance Dimension_Topics'!$B$3:$B$16,"None",0) -> Legal | O86: WTO Consistency & Legal Interpretation
A87: G/C/M/153 | B87: 46177 | C87: Minutes of the Meeting of the Council for Trade in Goods (27-28 Nov 2025) | D87: CTG | E87: United States | F87: Defence/Explanation | G87: Industrial Policy & Economic Security | H87: 10.3.24 | I87: National/Economic Security | L87: Disruptive Policy Measures on Semiconductors | M87: United States
A88: G/C/M/153 | B88: 46177 | C88: Minutes of the Meeting of the Council for Trade in Goods (27-28 Nov 2025) | D88: CTG | E88: China | F88: Concern Raised | G88: Industrial Policy & Economic Security | H88: 10.3.25 | I88: Export/Import Controls | L88: Disruptive Policy Measures on Semiconductors | M88: United States | N88: =_xlfn.XLOOKUP(O88,'Governance Dimension_Topics'!$C$3:$C$16,'Governance Dimension_Topics'!$B$3:$B$16,"None",0) -> Legal | O88: WTO Consistency & Legal Interpretation | P88: =_xlfn.XLOOKUP(Q88,'Governance Dimension_Topics'!$C$3:$C$16,'Governance Dimension_Topics'!$B$3:$B$16,"None",0) -> Economic | Q88: Competitiveness
A89: G/C/M/153 | B89: 46177 | C89: Minutes of the Meeting of the Council for Trade in Goods (27-28 Nov 2025) | D89: CTG | E89: Venezuela | F89: Concern Raised | G89: Industrial Policy & Economic Security | H89: 10.3.25 | I89: National/Economic Security | L89: Disruptive Policy Measures on Semiconductors | M89: United States | N89: =_xlfn.XLOOKUP(O89,'Governance Dimension_Topics'!$C$3:$C$16,'Governance Dimension_Topics'!$B$3:$B$16,"None",0) -> Legal | O89: WTO Consistency & Legal Interpretation | P89: =_xlfn.XLOOKUP(Q89,'Governance Dimension_Topics'!$C$3:$C$16,'Governance Dimension_Topics'!$B$3:$B$16,"None",0) -> Economic | Q89: Market Access & Trade Effects | R89: =_xlfn.XLOOKUP(S89,'[1]Governance Dimension_Topics'!$C$3:$C$16,'[1]Governance Dimension_Topics'!$B$3:$B$16,"None",0) -> Development | S89: Policy Space | T89: =_xlfn.XLOOKUP(U89,'[1]Governance Dimension_Topics'!$C$3:$C$16,'[1]Governance Dimension_Topics'!$B$3:$B$16,"None",0) -> Development | U89: Equity & Just Transition
A90: G/C/M/153 | B90: 46177 | C90: Minutes of the Meeting of the Council for Trade in Goods (27-28 Nov 2025) | D90: CTG | E90: United States | F90: Defence/Explanation | G90: Industrial Policy & Economic Security | H90: 10.3.25 | I90: National/Economic Security | L90: Disruptive Policy Measures on Semiconductors | M90: United States
A91: G/C/M/153 | B91: 46177 | C91: Minutes of the Meeting of the Council for Trade in Goods (27-28 Nov 2025) | D91: CTG | E91: Russian Federation | F91: Concern Raised | G91: Climate & Sustainability | H91: 10.3.26 | I91: Carbon Measures | J91: Other Climate/Sustainability Measures | K91: Deforestation & Biodiversity | L91: EU Green Deal | M91: European Union | N91: =_xlfn.XLOOKUP(O91,'Governance Dimension_Topics'!$C$3:$C$16,'Governance Dimension_Topics'!$B$3:$B$16,"None",0) -> Legal | O91: WTO Consistency & Legal Interpretation | X91: Medium | Y91: Criticized aspects of the European Green Deal as creating trade distortions and fragmentation through unilateral climate-related measures.
A92: G/C/M/153 | B92: 46177 | C92: Minutes of the Meeting of the Council for Trade in Goods (27-28 Nov 2025) | D92: CTG | E92: European Union | F92: Defence/Explanation | G92: Climate & Sustainability | H92: 10.3.26 | I92: Other Climate/Sustainability Measures | J92: Carbon Measures | K92: Deforestation & Biodiversity | L92: EU Green Deal | M92: European Union | X92: Medium | Y92: Defended the European Green Deal as a framework supporting decarbonization, sustainability and climate objectives.
A93: G/C/M/153 | B93: 46177 | C93: Minutes of the Meeting of the Council for Trade in Goods (27-28 Nov 2025) | D93: CTG | E93: Japan | F93: Concern Raised | G93: Industrial Policy & Economic Security | H93: 10.3.29 | I93: Export/Import Controls | J93: National/Economic Security | L93: Export Restrictions | M93: Indonesia | N93: =_xlfn.XLOOKUP(O93,'Governance Dimension_Topics'!$C$3:$C$16,'Governance Dimension_Topics'!$B$3:$B$16,"None",0) -> Political Economy | O93: Economic Security & Strategic Autonomy | X93: High | Y93: Raised concerns regarding Indonesian export restrictions and their effects on supply chains and access to raw materials.
A94: G/C/M/153 | B94: 46177 | C94: Minutes of the Meeting of the Council for Trade in Goods (27-28 Nov 2025) | D94: CTG | E94: UK | F94: Defence/Explanation | G94: Industrial Policy & Economic Security | H94: 10.3.29 | I94: Export/Import Controls | L94: Export Restrictions | M94: Indonesia
A95: G/C/M/153 | B95: 46177 | C95: Minutes of the Meeting of the Council for Trade in Goods (27-28 Nov 2025) | D95: CTG | E95: United States | F95: Concern Raised | G95: Industrial Policy & Economic Security | H95: 10.3.29 | I95: Localisation Measures | L95: Export Restrictions | M95: Indonesia
A96: G/C/M/153 | B96: 46177 | C96: Minutes of the Meeting of the Council for Trade in Goods (27-28 Nov 2025) | D96: CTG | E96: Indonesia | F96: Defence/Explanation | G96: Industrial Policy & Economic Security | H96: 10.3.29 | I96: National/Economic Security | J96: Export/Import Controls | L96: Export Restrictions | M96: Indonesia | X96: High | Y96: Defended export governance measures as necessary to safeguard domestic supply, support industrial development, downstream processing and economic resilience.
A97: G/TFA/W/143 | B97: 46176 | C97: Implementation of the MC14 Decision on the Work Programme on Small Economies | D97: CTF | E97: Guatemala (on behalf of the SVE Group) | F97: Proposal/Recommendation | G97: Digital Trade | H97: 2.1-3.2 | I97: E-Commerce | L97: No Specific Measure | M97: Not applicable | N97: =_xlfn.XLOOKUP(O97,'[1]Governance Dimension_Topics'!$C$3:$C$16,'[1]Governance Dimension_Topics'!$B$3:$B$16,"None",0) -> Institutional | O97: International Cooperation | P97: =_xlfn.XLOOKUP(Q97,'[1]Governance Dimension_Topics'!$C$3:$C$16,'[1]Governance Dimension_Topics'!$B$3:$B$16,"None",0) -> Institutional | Q97: Institutional Capacity & Coordination | R97: =_xlfn.XLOOKUP(S97,'[1]Governance Dimension_Topics'!$C$3:$C$16,'[1]Governance Dimension_Topics'!$B$3:$B$16,"None",0) -> Technical | S97: MRV methodologies | T97: =_xlfn.XLOOKUP(U97,'[1]Governance Dimension_Topics'!$C$3:$C$16,'[1]Governance Dimension_Topics'!$B$3:$B$16,"None",0) -> Legal | U97: WTO Consistency & Legal Interpretation | V97: =_xlfn.XLOOKUP(W97,'[1]Governance Dimension_Topics'!$C$3:$C$16,'[1]Governance Dimension_Topics'!$B$3:$B$16,"None",0) -> Development | W97: Capacity Constraints | X97: High | Y97: Proposed a dedicated Trade Facilitation Committee session on digital trade facilitation, transparency, traceability and coordination to implement the MC14 mandate for small economies.
A98: WT/COMTD/SE/M/50 | B98: 46038 | C98: NOTE ON THE MEETING: Fiftieth Dedicated Session on Small Economies | D98: CTD | E98: Guatemala (on behalf of the SVE Group) | F98: Information Sharing | G98: Climate & Sustainability | L98: No Specific Measure | M98: Not applicable
A99: WT/COMTD/SE/M/50 | B99: 46038 | C99: NOTE ON THE MEETING: Fiftieth Dedicated Session on Small Economies | D99: CTD | E99: Guatemala (on behalf of the SVE Group) | F99: Information Sharing | G99: Climate & Sustainability | I99: Other Climate/Sustainability Measures | L99: No Specific Measure | M99: Not applicable | N99: =_xlfn.XLOOKUP(O99,'[1]Governance Dimension_Topics'!$C$3:$C$16,'[1]Governance Dimension_Topics'!$B$3:$B$16,"None",0) -> Institutional | O99: International Cooperation
A100: WT/COMTD/SE/M/50 | B100: 46038 | C100: NOTE ON THE MEETING: Fiftieth Dedicated Session on Small Economies | D100: CTD | E100: Secretariat | F100: Information Sharing | G100: Climate & Sustainability | H100: 5-19 | I100: Other Climate/Sustainability Measures | L100: No Specific Measure | M100: Not applicable | N100: =_xlfn.XLOOKUP(O100,'[1]Governance Dimension_Topics'!$C$3:$C$16,'[1]Governance Dimension_Topics'!$B$3:$B$16,"None",0) -> Institutional | O100: International Cooperation | P100: =_xlfn.XLOOKUP(Q100,'[1]Governance Dimension_Topics'!$C$3:$C$16,'[1]Governance Dimension_Topics'!$B$3:$B$16,"None",0) -> Institutional | Q100: Institutional Capacity & Coordination | R100: =_xlfn.XLOOKUP(S100,'[1]Governance Dimension_Topics'!$C$3:$C$16,'[1]Governance Dimension_Topics'!$B$3:$B$16,"None",0) -> Development | S100: Policy Space | X100: High | Y100: Presented factual analysis on interface of trade and climate, environmental goods, climate finance and technology transfer for SVEs.
...

Sheet Domain
A1: Domain | B1: Sub-Domain | C1: Keywords / Alternative Terms
A2: Climate & Sustainability | B2: Carbon Measures | C2: CBAM; Carbon Border Adjustment; Carbon Border Adjustment Mechanism; Border Carbon Adjustment; Border Carbon Measures; Decarbonization; Decarbonisation; Net Zero
A3: Climate & Sustainability | B3: Deforestation & Biodiversity | C3: EUDR; Deforestation Regulation; Forest Risk Commodities; Biodiversity; Nature Protection; Ecosystem Protection
A4: Climate & Sustainability | B4: Other Climate/ Sustainability Measures | C4: Circular Economy; Eco-design; Ecodesign; Product Passport; Recycling Requirements; Recycled Content; Sustainability Standards; ESG Standards; Sustainability Reporting; Disclosure Requirements; Due Diligence; Supply Chain Due Diligence; Sustainability Standards; ESG Standards; Sustainability Reporting; Disclosure Requirements; Due Diligence; Supply Chain Due Diligence; Energy Transition; Green Hydrogen; Renewable Energy
A5: Digital Trade | B5: AI & Emerging Technologies | C5: Artificial Intelligence; AI; Algorithmic Systems; Machine Learning; Cybersecurity; Cyber Security; Digital Security
A6: Digital Trade | B6: E-Commerce | C6: E-Commerce; Electronic Commerce; Digital Trade; Online Platforms; Moratorium; Customs Duties on Electronic Transmissions; Electronic Transmissions; Cross-Border Data Flows; Data Transfers; Data Localisation; Data Localization; Data Governance
A7: Industrial Policy & Economic Security | B7: Subsidies | C7: Subsidies; State Aid; Government Support; Fiscal Incentives; Tax Credits; State Interventions
A8: Industrial Policy & Economic Security | B8: Green Policies | C8: Inflation Reduction Act; IRA; Clean Technology Support; Industrial Decarbonisation; Net-Zero Industry Policies
A9: Industrial Policy & Economic Security | B9: Localisation Measures | C9: Local Content Requirements; Domestic Content Requirements; Localization Requirements; Import Substitution
A10: Industrial Policy & Economic Security | B10: Government Procurement | C10: Public Procurement; Government Procurement; Buy National; Buy Local
A11: Industrial Policy & Economic Security | B11: National/Economic Security | C11: Critical Minerals; Rare Earths; Strategic Raw Materials; Supply Chain Resilience; Diversification; Friendshoring; Nearshoring; Trade Weaponisation
A12: Industrial Policy & Economic Security | B12: Export/Import Controls | C12: Export Controls; Export Restrictions; Technology Controls; Semiconductor Controls; Import Restrictions

Sheet Governance Dimension_Topics
B2: Governance Dimension | C2: Governance Topic | D2: Trigger Keywords | E2: Contextual Indicators
B3: Legal | C3: WTO Consistency & Legal Interpretation | D3: WTO-consistent, obligations, GATT, SCM, TBT, SPS, legal basis, WTO Consistency, MFN, national treatment, discrimination, equal treatment, Non-Discrimination, extraterritorial, outside jurisdiction, foreign producers, Extraterritoriality | E3: Discussion of whether measure conforms with WTO or international legal obligations
B4: Legal | C4: Transparency & Due Process | D4: transparency, notification, consultation, stakeholder engagement, Consumer Information, Disclosure Requirements, Consultation Process, Public Consultation, predictability, certainty, clarity, stable rules, HS Classification Reform, Scope Expansion, Scope Clarification, predictability, certainty, clarity, stable rules, HS Classification Reform, Scope Expansion, Scope Clarification | E4: Calls for advance notice, consultation, procedural fairness, predictability of rules, clarity on rules or measures
B5: Economic | C5: Market Access & Trade Effects | D5: market access, exports, imports, barriers, trade flows, Green Services, Trade Facilitation | E5: Measure affects ability to sell products internationally
B6: Economic | C6: Competitiveness | D6: competitiveness, level playing field, cost disadvantage, SMEs, small business, industry impacts, investment, jobs, relocation, employment, Investment Promotion | E6: Firms or sectors may gain/lose competitive position
B7: Economic | C7: Compliance Costs | D7: compliance cost, administrative burden, reporting burden, Border Carbon Adjustment, Border Carbon Adjustments, Carbon Pricing, ETS, Carbon Tax, Carbon Credits, Carbon Price Deduction, Compliance Costs | E7: Firms incur costs to meet requirements
B8: Development | C8: Capacity Constraints | D8: capacity, institutional constraints, readiness, Capacity Constraints, Technical capacity; Financial Capacity | E8: Developing countries lack ability to comply
B9: Development | C9: Equity & Just Transition | D9: fairness, equity, inclusiveness, just transition, Food Security, Traditional Knowledge, Climate Vulnerability, Sustainable Trade, Energy Transition, S&DT, CBDR, LDCs, developing countries, Small Economies | E9: Distributional effects across countries or groups
B10: Development | C10: Policy Space | D10: policy space, industrialisation, development priorities, Structural Constraints, Sustainable Development, Green Growth, domestic conditions | E10: Concern that measure restricts development choices
B11: Technical | C11: MRV methodologies | D11: MRV, emissions calculation, carbon intensity, monitoring, verification, reporting, Carbon Accounting, Carbon Measurement Standards, traceability, tracking, databases, product passport, Digital Services, methodology, benchmark, default values, certification, accreditation, verification, Verification Framework, ESG Standards, Conformity Assessment, Certification Schemes | E11: Debate on measuring emissions
B12: Technical | C12: Technical Basis | D12: science-based, evidence-based, risk assessment, Evidence Requirements | E12: Requests for scientific justification
B13: Regulatory | C13: Interoperability & Equivalence | D13: interoperability, equivalence, compatibility, harmonisation, alignment, common standards, Sustainability Standards, International Standards, Regulatory Alignment, Regulatory Architecture, Climate-Related Measures, Policy Alignment, mutual recognition, foreign standards, Recognition of Foreign Carbon Pricing Systems, Recognition of Foreign Regulatory Systems, Recognition of Foreign Systems, fragmentation, overlapping requirements, Biodiversity Governance, Access and Benefit Sharing, Bioeconomy Governance, Standards Fragmentation, Regulatory Coherence | E13: Different systems need to function together
... B16: Political Economy | C16: Economic Security & Strategic Autonomy | D16: economic security, strategic autonomy, resilience, industrial policy, friendshoring, reshoring, technology leadership, supply chain, value chain, sourcing, resilience, Green Supply Chains, Supply Chain Resilience, reciprocal tariffs, national security, economic security. | E16: Measure justified by security or strategic concerns
